
                <game>
                    <path>./hamster-slam.p8.png</path>
                    <name>Hamster Slam</name>
                    <image>./hamster-slam.p8.png</image>
                    <desc>
                        Description: Roll your hamster ball to knock others out of the ring. Last hamster standing wins. Supports one or two players.

                        Controls: * Arrow Keys - Move player one's hamster (green hamster ball)
* ESDF - In 2-player mode, move player two's hamster (red hamster ball)
* P - Pause menu. Allows selecting 2 player mode and activating/deactivating Super Bounce mode
* X - Start a new game when round ends
                    </desc>
                </game>
            